wuthery/l10n/__init__.py
wuthery/l10n/enums.py
wuthery/l10n/translator.py
wuthery_l10n-0.3.0.dist-info/LICENSE
wuthery_l10n-0.3.0.dist-info/METADATA
wuthery_l10n-0.3.0.dist-info/WHEEL
wuthery_l10n-0.3.0.dist-info/RECORD
