Metadata-Version: 2.1
Name: wuthery-l10n
Version: 0.3.0
Summary: Python package to interact with Wuthery's localization files.
License: GPL-3.0
Author: seria
Author-email: seria.ati@gmail.com
Requires-Python: >=3.12,<4.0
Classifier: License :: OSI Approved :: GNU General Public License v3 (GPLv3)
Classifier: Programming Language :: Python :: 3
Classifier: Programming Language :: Python :: 3.12
Requires-Dist: aiohttp (>=3.9.5,<4.0.0)
Requires-Dist: pyyaml (>=6.0.1,<7.0.0)
